{
  "Conta": {
    "Total": 1000,
    "Alocado": 973.19,
    "SaldoDisponivel": 0.0
  },
  "Fechados": {
    "PnLTotal": -26.81,
    "PnLPercent": -0.9
  },
  "Abertos": {
    "PnLEstimado": 16.2,
    "PnLEstimadoPercent": 1.66
  },
  "PosicaoGeral": {
    "PnLCombinado": -10.61,
    "PnLCombinadoPercent": -0.27
  },
  "BenchmarkSP500": 0,
  "MaxDrawdown": -7.77,
  "SharpeRatio": -0.07,
  "Expectancy": -1.17,
  "MetricasPorTrade": {
    "MediaPnL": -0.92,
    "RetornoConta": -2.68,
    "WinRate": 52.17,
    "MaiorLucro": {
      "Valor": 51.1,
      "Percent": 34.07
    },
    "MaiorPrejuizo": {
      "Valor": -25.63,
      "Percent": -17.09
    }
  },
  "Resumo": {
    "TotalTrades": 29,
    "DataPrimeiroTrade": "08/04/2025",
    "DiasUteis": 40
  },
  "Meta": {
    "Objetivo": 10000,
    "ValorAtual": -26.81,
    "Faltante": 10026.81,
    "PercentualAtingido": -0.27,
    "DiasUteisRestantes": 237,
    "ValorMedioDiarioNecessario": 42.31
  }
}